content_licencing/__init__.py
content_licencing/admin.py
content_licencing/apps.py
content_licencing/fields.py
content_licencing/forms.py
content_licencing/licences.py
content_licencing/mixins.py
content_licencing/models.py
content_licencing/settings.py
content_licencing/tests.py
content_licencing/view_mixins.py
content_licencing/views.py
content_licencing/widgets.py
content_licencing/migrations/0001_initial.py
content_licencing/migrations/__init__.py
content_licencing-0.5.0.dist-info/licenses/LICENSE
content_licencing-0.5.0.dist-info/METADATA
content_licencing-0.5.0.dist-info/WHEEL
content_licencing-0.5.0.dist-info/top_level.txt
content_licencing-0.5.0.dist-info/RECORD
