Metadata-Version: 2.4
Name: content_licencing
Version: 0.5.0
Summary: Content licencing for django
Home-page: https://github.com/SiSol-Systems/content-licencing
Author: Thomas Uher
Author-email: thomas.uher@sisol-systems.com
License: The MIT License
Keywords: django,licence
Platform: OS Independent
Classifier: Programming Language :: Python :: 3
Classifier: License :: OSI Approved :: MIT License
Classifier: Operating System :: OS Independent
Requires-Python: >=3.6
License-File: LICENSE
Dynamic: author
Dynamic: author-email
Dynamic: classifier
Dynamic: description
Dynamic: description-content-type
Dynamic: home-page
Dynamic: keywords
Dynamic: license
Dynamic: license-file
Dynamic: platform
Dynamic: requires-python
Dynamic: summary
